brave_mcp_langchain/__init__.py
brave_mcp_langchain/brave_tool.py
brave_mcp_langchain/helper.py
brave_mcp_langchain/server.py
brave_mcp_langchain-0.2.0.dist-info/METADATA
brave_mcp_langchain-0.2.0.dist-info/WHEEL
brave_mcp_langchain-0.2.0.dist-info/entry_points.txt
brave_mcp_langchain-0.2.0.dist-info/RECORD
