Metadata-Version: 2.4
Name: brave-mcp-langchain
Version: 0.2.0
Summary: A tool that can give you freedom of using Brave search and content fetching using MCP and Langchan
Project-URL: Homepage, https://github.com/iamatulsingh/brave-mcp-langchain
Project-URL: Issues, https://github.com/iamatulsingh/brave-mcp-langchain/issues
Classifier: Development Status :: 3 - Alpha
Classifier: Intended Audience :: Developers
Classifier: License :: OSI Approved :: MIT License
Classifier: Programming Language :: Python :: 3
Classifier: Programming Language :: Python :: 3.10
Classifier: Programming Language :: Python :: 3.11
Classifier: Programming Language :: Python :: 3.12
Classifier: Programming Language :: Python :: 3.13
Requires-Python: >=3.12
Requires-Dist: beautifulsoup4>=4.13.3
Requires-Dist: httpx>=0.28.1
Requires-Dist: langchain-core==0.3.68
Requires-Dist: langchain==0.3.26
Requires-Dist: mcp[cli]>=1.3.0
Requires-Dist: pydantic==2.11.7
Requires-Dist: starlette==0.47.1
Requires-Dist: uvicorn==0.35.0
